LICENSE
MANIFEST.in
README.rst
setup.py
django_oauth2_provider.egg-info/PKG-INFO
django_oauth2_provider.egg-info/SOURCES.txt
django_oauth2_provider.egg-info/dependency_links.txt
django_oauth2_provider.egg-info/not-zip-safe
django_oauth2_provider.egg-info/requires.txt
django_oauth2_provider.egg-info/top_level.txt
provider/__init__.py
provider/constants.py
provider/forms.py
provider/models.py
provider/scope.py
provider/sphinx.py
provider/urls.py
provider/utils.py
provider/views.py
provider/compat/__init__.py
provider/compat/urls.py
provider/oauth2/__init__.py
provider/oauth2/admin.py
provider/oauth2/backends.py
provider/oauth2/forms.py
provider/oauth2/managers.py
provider/oauth2/models.py
provider/oauth2/tests.py
provider/oauth2/urls.py
provider/oauth2/views.py
provider/oauth2/fixtures/test_oauth2.json
provider/oauth2/migrations/0001_initial.py
provider/oauth2/migrations/0002_auto__chg_field_client_user.py
provider/oauth2/migrations/0003_auto__add_field_client_name.py
provider/oauth2/migrations/__init__.py
provider/templates/provider/authorize.html
provider/templatetags/__init__.py
provider/templatetags/scope.py
tests/__init__.py
tests/settings.py
tests/urls.py