Metadata-Version: 1.1
Name: django-oauth2-provider
Version: 0.2.5
Summary: Provide OAuth2 access to your app
Home-page: https://github.com/caffeinehit/django-oauth2-provider
Author: Alen Mujezinovic
Author-email: alen@caffeinehit.com
License: UNKNOWN
Platform: UNKNOWN
Classifier: Environment :: Web Environment
Classifier: Intended Audience :: Developers
Classifier: License :: OSI Approved :: BSD License
Classifier: Operating System :: OS Independent
Classifier: Programming Language :: Python
Classifier: Framework :: Django
